clientTest/__init__.py
clientTest/__main__.py
clientTest/utils.py
example1_pkg_rich-0.0.2.dist-info/LICENSE
example1_pkg_rich-0.0.2.dist-info/METADATA
example1_pkg_rich-0.0.2.dist-info/WHEEL
example1_pkg_rich-0.0.2.dist-info/top_level.txt
example1_pkg_rich-0.0.2.dist-info/RECORD
