Metadata-Version: 2.1
Name: example1-pkg-rich
Version: 0.0.2
Summary: A small example package
Home-page: https://github.com/RicardoLR/demo-pip-sample
Author: Rich
Author-email: rich@test.com
License: UNKNOWN
Platform: UNKNOWN
Classifier: Programming Language :: Python :: 3
Classifier: License :: OSI Approved :: MIT License
Classifier: Operating System :: OS Independent
